pynurbs/__classes__.py
pynurbs/__init__.py
pynurbs/advanced.py
pynurbs/calculus.py
pynurbs/curves.py
pynurbs/functions.py
pynurbs/heavy.py
pynurbs/knotspace.py
pynurbs-1.1.0.dist-info/LICENSE.md
pynurbs-1.1.0.dist-info/METADATA
pynurbs-1.1.0.dist-info/WHEEL
pynurbs-1.1.0.dist-info/RECORD
