Metadata-Version: 2.1
Name: pynurbs
Version: 1.1.0
Summary: NURBS python object-oriented library
Author: Carlos Adir
Author-email: carlos.adir.leite@gmail.com
Requires-Python: >=3.7,<4.0
Classifier: Programming Language :: Python :: 3
Classifier: Programming Language :: Python :: 3.7
Classifier: Programming Language :: Python :: 3.8
Classifier: Programming Language :: Python :: 3.9
Classifier: Programming Language :: Python :: 3.10
Classifier: Programming Language :: Python :: 3.11
Classifier: Programming Language :: Python :: 3.12
